{
  "id": "673410aa-fd16-48f9-bb47-b3c24fda9d2f",
  "prevId": "00000000-0000-0000-0000-000000000000",
  "version": "7",
  "dialect": "postgresql",
  "tables": {
    "public.accounts": {
      "name": "accounts",
      "schema": "",
      "columns": {
        "user_id": {
          "name": "user_id",
          "type": "uuid",
          "primaryKey": false,
          "notNull": true
        },
        "type": {
          "name": "type",
          "type": "text",
          "primaryKey": false,
          "notNull": true
        },
        "provider": {
          "name": "provider",
          "type": "text",
          "primaryKey": false,
          "notNull": true
        },
        "provider_account_id": {
          "name": "provider_account_id",
          "type": "text",
          "primaryKey": false,
          "notNull": true
        },
        "refresh_token": {
          "name": "refresh_token",
          "type": "text",
          "primaryKey": false,
          "notNull": false
        },
        "access_token": {
          "name": "access_token",
          "type": "text",
          "primaryKey": false,
          "notNull": false
        },
        "expires_at": {
          "name": "expires_at",
          "type": "integer",
          "primaryKey": false,
          "notNull": false
        },
        "token_type": {
          "name": "token_type",
          "type": "text",
          "primaryKey": false,
          "notNull": false
        },
        "scope": {
          "name": "scope",
          "type": "text",
          "primaryKey": false,
          "notNull": false
        },
        "id_token": {
          "name": "id_token",
          "type": "text",
          "primaryKey": false,
          "notNull": false
        },
        "session_state": {
          "name": "session_state",
          "type": "text",
          "primaryKey": false,
          "notNull": false
        }
      },
      "indexes": {
        "account_compound_idx": {
          "name": "account_compound_idx",
          "columns": [
            {
              "expression": "provider",
              "isExpression": false,
              "asc": true,
              "nulls": "last"
            },
            {
              "expression": "provider_account_id",
              "isExpression": false,
              "asc": true,
              "nulls": "last"
            }
          ],
          "isUnique": false,
          "concurrently": false,
          "method": "btree",
          "with": {}
        }
      },
      "foreignKeys": {
        "accounts_user_id_users_id_fk": {
          "name": "accounts_user_id_users_id_fk",
          "tableFrom": "accounts",
          "tableTo": "users",
          "columnsFrom": [
            "user_id"
          ],
          "columnsTo": [
            "id"
          ],
          "onDelete": "cascade",
          "onUpdate": "no action"
        }
      },
      "compositePrimaryKeys": {},
      "uniqueConstraints": {},
      "policies": {},
      "checkConstraints": {},
      "isRLSEnabled": false
    },
    "public.buildings": {
      "name": "buildings",
      "schema": "",
      "columns": {
        "id": {
          "name": "id",
          "type": "uuid",
          "primaryKey": true,
          "notNull": true,
          "default": "gen_random_uuid()"
        },
        "organization_id": {
          "name": "organization_id",
          "type": "uuid",
          "primaryKey": false,
          "notNull": true
        },
        "name": {
          "name": "name",
          "type": "text",
          "primaryKey": false,
          "notNull": true
        },
        "address": {
          "name": "address",
          "type": "text",
          "primaryKey": false,
          "notNull": true
        },
        "city": {
          "name": "city",
          "type": "text",
          "primaryKey": false,
          "notNull": true
        },
        "postal_code": {
          "name": "postal_code",
          "type": "text",
          "primaryKey": false,
          "notNull": true
        },
        "country": {
          "name": "country",
          "type": "text",
          "primaryKey": false,
          "notNull": false,
          "default": "'Germany'"
        },
        "total_units": {
          "name": "total_units",
          "type": "integer",
          "primaryKey": false,
          "notNull": true
        },
        "year_built": {
          "name": "year_built",
          "type": "integer",
          "primaryKey": false,
          "notNull": false
        },
        "property_type": {
          "name": "property_type",
          "type": "text",
          "primaryKey": false,
          "notNull": false,
          "default": "'apartment'"
        },
        "created_at": {
          "name": "created_at",
          "type": "timestamp with time zone",
          "primaryKey": false,
          "notNull": false,
          "default": "now()"
        },
        "updated_at": {
          "name": "updated_at",
          "type": "timestamp with time zone",
          "primaryKey": false,
          "notNull": false,
          "default": "now()"
        }
      },
      "indexes": {
        "building_org_idx": {
          "name": "building_org_idx",
          "columns": [
            {
              "expression": "organization_id",
              "isExpression": false,
              "asc": true,
              "nulls": "last"
            }
          ],
          "isUnique": false,
          "concurrently": false,
          "method": "btree",
          "with": {}
        }
      },
      "foreignKeys": {
        "buildings_organization_id_organizations_id_fk": {
          "name": "buildings_organization_id_organizations_id_fk",
          "tableFrom": "buildings",
          "tableTo": "organizations",
          "columnsFrom": [
            "organization_id"
          ],
          "columnsTo": [
            "id"
          ],
          "onDelete": "no action",
          "onUpdate": "no action"
        }
      },
      "compositePrimaryKeys": {},
      "uniqueConstraints": {},
      "policies": {},
      "checkConstraints": {},
      "isRLSEnabled": false
    },
    "public.consumption_records": {
      "name": "consumption_records",
      "schema": "",
      "columns": {
        "id": {
          "name": "id",
          "type": "uuid",
          "primaryKey": true,
          "notNull": true,
          "default": "gen_random_uuid()"
        },
        "organization_id": {
          "name": "organization_id",
          "type": "uuid",
          "primaryKey": false,
          "notNull": true
        },
        "contract_id": {
          "name": "contract_id",
          "type": "uuid",
          "primaryKey": false,
          "notNull": true
        },
        "consumption_type": {
          "name": "consumption_type",
          "type": "text",
          "primaryKey": false,
          "notNull": true
        },
        "period": {
          "name": "period",
          "type": "text",
          "primaryKey": false,
          "notNull": true
        },
        "reading": {
          "name": "reading",
          "type": "numeric(12, 3)",
          "primaryKey": false,
          "notNull": true
        },
        "unit": {
          "name": "unit",
          "type": "text",
          "primaryKey": false,
          "notNull": true
        },
        "cost": {
          "name": "cost",
          "type": "numeric(10, 2)",
          "primaryKey": false,
          "notNull": false
        },
        "meter_number": {
          "name": "meter_number",
          "type": "text",
          "primaryKey": false,
          "notNull": false
        },
        "reading_date": {
          "name": "reading_date",
          "type": "timestamp with time zone",
          "primaryKey": false,
          "notNull": true
        },
        "created_at": {
          "name": "created_at",
          "type": "timestamp with time zone",
          "primaryKey": false,
          "notNull": false,
          "default": "now()"
        },
        "updated_at": {
          "name": "updated_at",
          "type": "timestamp with time zone",
          "primaryKey": false,
          "notNull": false,
          "default": "now()"
        }
      },
      "indexes": {
        "consumption_org_idx": {
          "name": "consumption_org_idx",
          "columns": [
            {
              "expression": "organization_id",
              "isExpression": false,
              "asc": true,
              "nulls": "last"
            }
          ],
          "isUnique": false,
          "concurrently": false,
          "method": "btree",
          "with": {}
        },
        "consumption_contract_idx": {
          "name": "consumption_contract_idx",
          "columns": [
            {
              "expression": "contract_id",
              "isExpression": false,
              "asc": true,
              "nulls": "last"
            }
          ],
          "isUnique": false,
          "concurrently": false,
          "method": "btree",
          "with": {}
        },
        "consumption_period_idx": {
          "name": "consumption_period_idx",
          "columns": [
            {
              "expression": "period",
              "isExpression": false,
              "asc": true,
              "nulls": "last"
            }
          ],
          "isUnique": false,
          "concurrently": false,
          "method": "btree",
          "with": {}
        }
      },
      "foreignKeys": {
        "consumption_records_organization_id_organizations_id_fk": {
          "name": "consumption_records_organization_id_organizations_id_fk",
          "tableFrom": "consumption_records",
          "tableTo": "organizations",
          "columnsFrom": [
            "organization_id"
          ],
          "columnsTo": [
            "id"
          ],
          "onDelete": "no action",
          "onUpdate": "no action"
        },
        "consumption_records_contract_id_contracts_id_fk": {
          "name": "consumption_records_contract_id_contracts_id_fk",
          "tableFrom": "consumption_records",
          "tableTo": "contracts",
          "columnsFrom": [
            "contract_id"
          ],
          "columnsTo": [
            "id"
          ],
          "onDelete": "no action",
          "onUpdate": "no action"
        }
      },
      "compositePrimaryKeys": {},
      "uniqueConstraints": {},
      "policies": {},
      "checkConstraints": {},
      "isRLSEnabled": false
    },
    "public.contracts": {
      "name": "contracts",
      "schema": "",
      "columns": {
        "id": {
          "name": "id",
          "type": "uuid",
          "primaryKey": true,
          "notNull": true,
          "default": "gen_random_uuid()"
        },
        "organization_id": {
          "name": "organization_id",
          "type": "uuid",
          "primaryKey": false,
          "notNull": true
        },
        "building_id": {
          "name": "building_id",
          "type": "uuid",
          "primaryKey": false,
          "notNull": true
        },
        "contract_number": {
          "name": "contract_number",
          "type": "text",
          "primaryKey": false,
          "notNull": true
        },
        "unit_number": {
          "name": "unit_number",
          "type": "text",
          "primaryKey": false,
          "notNull": true
        },
        "start_date": {
          "name": "start_date",
          "type": "timestamp with time zone",
          "primaryKey": false,
          "notNull": true
        },
        "end_date": {
          "name": "end_date",
          "type": "timestamp with time zone",
          "primaryKey": false,
          "notNull": false
        },
        "rent_amount": {
          "name": "rent_amount",
          "type": "numeric(10, 2)",
          "primaryKey": false,
          "notNull": true
        },
        "deposit_amount": {
          "name": "deposit_amount",
          "type": "numeric(10, 2)",
          "primaryKey": false,
          "notNull": false
        },
        "is_active": {
          "name": "is_active",
          "type": "boolean",
          "primaryKey": false,
          "notNull": false,
          "default": true
        },
        "contract_file_url": {
          "name": "contract_file_url",
          "type": "text",
          "primaryKey": false,
          "notNull": false
        },
        "created_at": {
          "name": "created_at",
          "type": "timestamp with time zone",
          "primaryKey": false,
          "notNull": false,
          "default": "now()"
        },
        "updated_at": {
          "name": "updated_at",
          "type": "timestamp with time zone",
          "primaryKey": false,
          "notNull": false,
          "default": "now()"
        }
      },
      "indexes": {
        "contract_org_idx": {
          "name": "contract_org_idx",
          "columns": [
            {
              "expression": "organization_id",
              "isExpression": false,
              "asc": true,
              "nulls": "last"
            }
          ],
          "isUnique": false,
          "concurrently": false,
          "method": "btree",
          "with": {}
        },
        "contract_building_idx": {
          "name": "contract_building_idx",
          "columns": [
            {
              "expression": "building_id",
              "isExpression": false,
              "asc": true,
              "nulls": "last"
            }
          ],
          "isUnique": false,
          "concurrently": false,
          "method": "btree",
          "with": {}
        },
        "contract_number_idx": {
          "name": "contract_number_idx",
          "columns": [
            {
              "expression": "contract_number",
              "isExpression": false,
              "asc": true,
              "nulls": "last"
            }
          ],
          "isUnique": false,
          "concurrently": false,
          "method": "btree",
          "with": {}
        }
      },
      "foreignKeys": {
        "contracts_organization_id_organizations_id_fk": {
          "name": "contracts_organization_id_organizations_id_fk",
          "tableFrom": "contracts",
          "tableTo": "organizations",
          "columnsFrom": [
            "organization_id"
          ],
          "columnsTo": [
            "id"
          ],
          "onDelete": "no action",
          "onUpdate": "no action"
        },
        "contracts_building_id_buildings_id_fk": {
          "name": "contracts_building_id_buildings_id_fk",
          "tableFrom": "contracts",
          "tableTo": "buildings",
          "columnsFrom": [
            "building_id"
          ],
          "columnsTo": [
            "id"
          ],
          "onDelete": "no action",
          "onUpdate": "no action"
        }
      },
      "compositePrimaryKeys": {},
      "uniqueConstraints": {},
      "policies": {},
      "checkConstraints": {},
      "isRLSEnabled": false
    },
    "public.documents": {
      "name": "documents",
      "schema": "",
      "columns": {
        "id": {
          "name": "id",
          "type": "uuid",
          "primaryKey": true,
          "notNull": true,
          "default": "gen_random_uuid()"
        },
        "organization_id": {
          "name": "organization_id",
          "type": "uuid",
          "primaryKey": false,
          "notNull": true
        },
        "building_id": {
          "name": "building_id",
          "type": "uuid",
          "primaryKey": false,
          "notNull": false
        },
        "contract_id": {
          "name": "contract_id",
          "type": "uuid",
          "primaryKey": false,
          "notNull": false
        },
        "ticket_id": {
          "name": "ticket_id",
          "type": "uuid",
          "primaryKey": false,
          "notNull": false
        },
        "uploaded_by_id": {
          "name": "uploaded_by_id",
          "type": "uuid",
          "primaryKey": false,
          "notNull": true
        },
        "file_name": {
          "name": "file_name",
          "type": "text",
          "primaryKey": false,
          "notNull": true
        },
        "original_file_name": {
          "name": "original_file_name",
          "type": "text",
          "primaryKey": false,
          "notNull": true
        },
        "file_size": {
          "name": "file_size",
          "type": "integer",
          "primaryKey": false,
          "notNull": true
        },
        "mime_type": {
          "name": "mime_type",
          "type": "text",
          "primaryKey": false,
          "notNull": true
        },
        "file_url": {
          "name": "file_url",
          "type": "text",
          "primaryKey": false,
          "notNull": true
        },
        "category": {
          "name": "category",
          "type": "text",
          "primaryKey": false,
          "notNull": false,
          "default": "'document'"
        },
        "description": {
          "name": "description",
          "type": "text",
          "primaryKey": false,
          "notNull": false
        },
        "is_public": {
          "name": "is_public",
          "type": "boolean",
          "primaryKey": false,
          "notNull": false,
          "default": false
        },
        "created_at": {
          "name": "created_at",
          "type": "timestamp with time zone",
          "primaryKey": false,
          "notNull": false,
          "default": "now()"
        }
      },
      "indexes": {
        "document_org_idx": {
          "name": "document_org_idx",
          "columns": [
            {
              "expression": "organization_id",
              "isExpression": false,
              "asc": true,
              "nulls": "last"
            }
          ],
          "isUnique": false,
          "concurrently": false,
          "method": "btree",
          "with": {}
        },
        "document_building_idx": {
          "name": "document_building_idx",
          "columns": [
            {
              "expression": "building_id",
              "isExpression": false,
              "asc": true,
              "nulls": "last"
            }
          ],
          "isUnique": false,
          "concurrently": false,
          "method": "btree",
          "with": {}
        },
        "document_contract_idx": {
          "name": "document_contract_idx",
          "columns": [
            {
              "expression": "contract_id",
              "isExpression": false,
              "asc": true,
              "nulls": "last"
            }
          ],
          "isUnique": false,
          "concurrently": false,
          "method": "btree",
          "with": {}
        }
      },
      "foreignKeys": {
        "documents_organization_id_organizations_id_fk": {
          "name": "documents_organization_id_organizations_id_fk",
          "tableFrom": "documents",
          "tableTo": "organizations",
          "columnsFrom": [
            "organization_id"
          ],
          "columnsTo": [
            "id"
          ],
          "onDelete": "no action",
          "onUpdate": "no action"
        },
        "documents_building_id_buildings_id_fk": {
          "name": "documents_building_id_buildings_id_fk",
          "tableFrom": "documents",
          "tableTo": "buildings",
          "columnsFrom": [
            "building_id"
          ],
          "columnsTo": [
            "id"
          ],
          "onDelete": "no action",
          "onUpdate": "no action"
        },
        "documents_contract_id_contracts_id_fk": {
          "name": "documents_contract_id_contracts_id_fk",
          "tableFrom": "documents",
          "tableTo": "contracts",
          "columnsFrom": [
            "contract_id"
          ],
          "columnsTo": [
            "id"
          ],
          "onDelete": "no action",
          "onUpdate": "no action"
        },
        "documents_ticket_id_tickets_id_fk": {
          "name": "documents_ticket_id_tickets_id_fk",
          "tableFrom": "documents",
          "tableTo": "tickets",
          "columnsFrom": [
            "ticket_id"
          ],
          "columnsTo": [
            "id"
          ],
          "onDelete": "no action",
          "onUpdate": "no action"
        },
        "documents_uploaded_by_id_users_id_fk": {
          "name": "documents_uploaded_by_id_users_id_fk",
          "tableFrom": "documents",
          "tableTo": "users",
          "columnsFrom": [
            "uploaded_by_id"
          ],
          "columnsTo": [
            "id"
          ],
          "onDelete": "no action",
          "onUpdate": "no action"
        }
      },
      "compositePrimaryKeys": {},
      "uniqueConstraints": {},
      "policies": {},
      "checkConstraints": {},
      "isRLSEnabled": false
    },
    "public.invitation_tokens": {
      "name": "invitation_tokens",
      "schema": "",
      "columns": {
        "id": {
          "name": "id",
          "type": "uuid",
          "primaryKey": true,
          "notNull": true,
          "default": "gen_random_uuid()"
        },
        "organization_id": {
          "name": "organization_id",
          "type": "uuid",
          "primaryKey": false,
          "notNull": true
        },
        "contract_id": {
          "name": "contract_id",
          "type": "uuid",
          "primaryKey": false,
          "notNull": true
        },
        "token": {
          "name": "token",
          "type": "text",
          "primaryKey": false,
          "notNull": true
        },
        "email": {
          "name": "email",
          "type": "text",
          "primaryKey": false,
          "notNull": true
        },
        "tenant_name": {
          "name": "tenant_name",
          "type": "text",
          "primaryKey": false,
          "notNull": false
        },
        "percentage": {
          "name": "percentage",
          "type": "numeric(5, 2)",
          "primaryKey": false,
          "notNull": false,
          "default": "'100.00'"
        },
        "is_main_tenant": {
          "name": "is_main_tenant",
          "type": "boolean",
          "primaryKey": false,
          "notNull": false,
          "default": false
        },
        "expires_at": {
          "name": "expires_at",
          "type": "timestamp with time zone",
          "primaryKey": false,
          "notNull": true
        },
        "used_at": {
          "name": "used_at",
          "type": "timestamp with time zone",
          "primaryKey": false,
          "notNull": false
        },
        "created_by_id": {
          "name": "created_by_id",
          "type": "uuid",
          "primaryKey": false,
          "notNull": true
        },
        "created_at": {
          "name": "created_at",
          "type": "timestamp with time zone",
          "primaryKey": false,
          "notNull": false,
          "default": "now()"
        }
      },
      "indexes": {
        "invitation_token_idx": {
          "name": "invitation_token_idx",
          "columns": [
            {
              "expression": "token",
              "isExpression": false,
              "asc": true,
              "nulls": "last"
            }
          ],
          "isUnique": false,
          "concurrently": false,
          "method": "btree",
          "with": {}
        },
        "invitation_org_idx": {
          "name": "invitation_org_idx",
          "columns": [
            {
              "expression": "organization_id",
              "isExpression": false,
              "asc": true,
              "nulls": "last"
            }
          ],
          "isUnique": false,
          "concurrently": false,
          "method": "btree",
          "with": {}
        }
      },
      "foreignKeys": {
        "invitation_tokens_organization_id_organizations_id_fk": {
          "name": "invitation_tokens_organization_id_organizations_id_fk",
          "tableFrom": "invitation_tokens",
          "tableTo": "organizations",
          "columnsFrom": [
            "organization_id"
          ],
          "columnsTo": [
            "id"
          ],
          "onDelete": "no action",
          "onUpdate": "no action"
        },
        "invitation_tokens_contract_id_contracts_id_fk": {
          "name": "invitation_tokens_contract_id_contracts_id_fk",
          "tableFrom": "invitation_tokens",
          "tableTo": "contracts",
          "columnsFrom": [
            "contract_id"
          ],
          "columnsTo": [
            "id"
          ],
          "onDelete": "no action",
          "onUpdate": "no action"
        },
        "invitation_tokens_created_by_id_users_id_fk": {
          "name": "invitation_tokens_created_by_id_users_id_fk",
          "tableFrom": "invitation_tokens",
          "tableTo": "users",
          "columnsFrom": [
            "created_by_id"
          ],
          "columnsTo": [
            "id"
          ],
          "onDelete": "no action",
          "onUpdate": "no action"
        }
      },
      "compositePrimaryKeys": {},
      "uniqueConstraints": {
        "invitation_tokens_token_unique": {
          "name": "invitation_tokens_token_unique",
          "nullsNotDistinct": false,
          "columns": [
            "token"
          ]
        }
      },
      "policies": {},
      "checkConstraints": {},
      "isRLSEnabled": false
    },
    "public.organizations": {
      "name": "organizations",
      "schema": "",
      "columns": {
        "id": {
          "name": "id",
          "type": "uuid",
          "primaryKey": true,
          "notNull": true,
          "default": "gen_random_uuid()"
        },
        "name": {
          "name": "name",
          "type": "text",
          "primaryKey": false,
          "notNull": true
        },
        "slug": {
          "name": "slug",
          "type": "text",
          "primaryKey": false,
          "notNull": true
        },
        "contact_email": {
          "name": "contact_email",
          "type": "text",
          "primaryKey": false,
          "notNull": true
        },
        "contact_phone": {
          "name": "contact_phone",
          "type": "text",
          "primaryKey": false,
          "notNull": false
        },
        "address": {
          "name": "address",
          "type": "text",
          "primaryKey": false,
          "notNull": false
        },
        "city": {
          "name": "city",
          "type": "text",
          "primaryKey": false,
          "notNull": false
        },
        "postal_code": {
          "name": "postal_code",
          "type": "text",
          "primaryKey": false,
          "notNull": false
        },
        "country": {
          "name": "country",
          "type": "text",
          "primaryKey": false,
          "notNull": false,
          "default": "'Germany'"
        },
        "created_at": {
          "name": "created_at",
          "type": "timestamp with time zone",
          "primaryKey": false,
          "notNull": false,
          "default": "now()"
        },
        "updated_at": {
          "name": "updated_at",
          "type": "timestamp with time zone",
          "primaryKey": false,
          "notNull": false,
          "default": "now()"
        }
      },
      "indexes": {
        "org_slug_idx": {
          "name": "org_slug_idx",
          "columns": [
            {
              "expression": "slug",
              "isExpression": false,
              "asc": true,
              "nulls": "last"
            }
          ],
          "isUnique": false,
          "concurrently": false,
          "method": "btree",
          "with": {}
        }
      },
      "foreignKeys": {},
      "compositePrimaryKeys": {},
      "uniqueConstraints": {
        "organizations_slug_unique": {
          "name": "organizations_slug_unique",
          "nullsNotDistinct": false,
          "columns": [
            "slug"
          ]
        }
      },
      "policies": {},
      "checkConstraints": {},
      "isRLSEnabled": false
    },
    "public.sessions": {
      "name": "sessions",
      "schema": "",
      "columns": {
        "session_token": {
          "name": "session_token",
          "type": "text",
          "primaryKey": true,
          "notNull": true
        },
        "user_id": {
          "name": "user_id",
          "type": "uuid",
          "primaryKey": false,
          "notNull": true
        },
        "expires": {
          "name": "expires",
          "type": "timestamp with time zone",
          "primaryKey": false,
          "notNull": true
        }
      },
      "indexes": {},
      "foreignKeys": {
        "sessions_user_id_users_id_fk": {
          "name": "sessions_user_id_users_id_fk",
          "tableFrom": "sessions",
          "tableTo": "users",
          "columnsFrom": [
            "user_id"
          ],
          "columnsTo": [
            "id"
          ],
          "onDelete": "cascade",
          "onUpdate": "no action"
        }
      },
      "compositePrimaryKeys": {},
      "uniqueConstraints": {},
      "policies": {},
      "checkConstraints": {},
      "isRLSEnabled": false
    },
    "public.tenant_contracts": {
      "name": "tenant_contracts",
      "schema": "",
      "columns": {
        "id": {
          "name": "id",
          "type": "uuid",
          "primaryKey": true,
          "notNull": true,
          "default": "gen_random_uuid()"
        },
        "organization_id": {
          "name": "organization_id",
          "type": "uuid",
          "primaryKey": false,
          "notNull": true
        },
        "tenant_id": {
          "name": "tenant_id",
          "type": "uuid",
          "primaryKey": false,
          "notNull": true
        },
        "contract_id": {
          "name": "contract_id",
          "type": "uuid",
          "primaryKey": false,
          "notNull": true
        },
        "percentage": {
          "name": "percentage",
          "type": "numeric(5, 2)",
          "primaryKey": false,
          "notNull": false,
          "default": "'100.00'"
        },
        "is_main_tenant": {
          "name": "is_main_tenant",
          "type": "boolean",
          "primaryKey": false,
          "notNull": false,
          "default": false
        },
        "created_at": {
          "name": "created_at",
          "type": "timestamp with time zone",
          "primaryKey": false,
          "notNull": false,
          "default": "now()"
        }
      },
      "indexes": {
        "tenant_contract_org_idx": {
          "name": "tenant_contract_org_idx",
          "columns": [
            {
              "expression": "organization_id",
              "isExpression": false,
              "asc": true,
              "nulls": "last"
            }
          ],
          "isUnique": false,
          "concurrently": false,
          "method": "btree",
          "with": {}
        },
        "tenant_contract_tenant_idx": {
          "name": "tenant_contract_tenant_idx",
          "columns": [
            {
              "expression": "tenant_id",
              "isExpression": false,
              "asc": true,
              "nulls": "last"
            }
          ],
          "isUnique": false,
          "concurrently": false,
          "method": "btree",
          "with": {}
        },
        "tenant_contract_contract_idx": {
          "name": "tenant_contract_contract_idx",
          "columns": [
            {
              "expression": "contract_id",
              "isExpression": false,
              "asc": true,
              "nulls": "last"
            }
          ],
          "isUnique": false,
          "concurrently": false,
          "method": "btree",
          "with": {}
        }
      },
      "foreignKeys": {
        "tenant_contracts_organization_id_organizations_id_fk": {
          "name": "tenant_contracts_organization_id_organizations_id_fk",
          "tableFrom": "tenant_contracts",
          "tableTo": "organizations",
          "columnsFrom": [
            "organization_id"
          ],
          "columnsTo": [
            "id"
          ],
          "onDelete": "no action",
          "onUpdate": "no action"
        },
        "tenant_contracts_tenant_id_users_id_fk": {
          "name": "tenant_contracts_tenant_id_users_id_fk",
          "tableFrom": "tenant_contracts",
          "tableTo": "users",
          "columnsFrom": [
            "tenant_id"
          ],
          "columnsTo": [
            "id"
          ],
          "onDelete": "no action",
          "onUpdate": "no action"
        },
        "tenant_contracts_contract_id_contracts_id_fk": {
          "name": "tenant_contracts_contract_id_contracts_id_fk",
          "tableFrom": "tenant_contracts",
          "tableTo": "contracts",
          "columnsFrom": [
            "contract_id"
          ],
          "columnsTo": [
            "id"
          ],
          "onDelete": "no action",
          "onUpdate": "no action"
        }
      },
      "compositePrimaryKeys": {},
      "uniqueConstraints": {},
      "policies": {},
      "checkConstraints": {},
      "isRLSEnabled": false
    },
    "public.tickets": {
      "name": "tickets",
      "schema": "",
      "columns": {
        "id": {
          "name": "id",
          "type": "uuid",
          "primaryKey": true,
          "notNull": true,
          "default": "gen_random_uuid()"
        },
        "organization_id": {
          "name": "organization_id",
          "type": "uuid",
          "primaryKey": false,
          "notNull": true
        },
        "building_id": {
          "name": "building_id",
          "type": "uuid",
          "primaryKey": false,
          "notNull": true
        },
        "contract_id": {
          "name": "contract_id",
          "type": "uuid",
          "primaryKey": false,
          "notNull": false
        },
        "created_by_id": {
          "name": "created_by_id",
          "type": "uuid",
          "primaryKey": false,
          "notNull": true
        },
        "assigned_to_id": {
          "name": "assigned_to_id",
          "type": "uuid",
          "primaryKey": false,
          "notNull": false
        },
        "title": {
          "name": "title",
          "type": "text",
          "primaryKey": false,
          "notNull": true
        },
        "description": {
          "name": "description",
          "type": "text",
          "primaryKey": false,
          "notNull": true
        },
        "priority": {
          "name": "priority",
          "type": "text",
          "primaryKey": false,
          "notNull": false,
          "default": "'medium'"
        },
        "status": {
          "name": "status",
          "type": "text",
          "primaryKey": false,
          "notNull": false,
          "default": "'open'"
        },
        "category": {
          "name": "category",
          "type": "text",
          "primaryKey": false,
          "notNull": false,
          "default": "'maintenance'"
        },
        "estimated_cost": {
          "name": "estimated_cost",
          "type": "numeric(10, 2)",
          "primaryKey": false,
          "notNull": false
        },
        "actual_cost": {
          "name": "actual_cost",
          "type": "numeric(10, 2)",
          "primaryKey": false,
          "notNull": false
        },
        "due_date": {
          "name": "due_date",
          "type": "timestamp with time zone",
          "primaryKey": false,
          "notNull": false
        },
        "resolved_at": {
          "name": "resolved_at",
          "type": "timestamp with time zone",
          "primaryKey": false,
          "notNull": false
        },
        "created_at": {
          "name": "created_at",
          "type": "timestamp with time zone",
          "primaryKey": false,
          "notNull": false,
          "default": "now()"
        },
        "updated_at": {
          "name": "updated_at",
          "type": "timestamp with time zone",
          "primaryKey": false,
          "notNull": false,
          "default": "now()"
        }
      },
      "indexes": {
        "ticket_org_idx": {
          "name": "ticket_org_idx",
          "columns": [
            {
              "expression": "organization_id",
              "isExpression": false,
              "asc": true,
              "nulls": "last"
            }
          ],
          "isUnique": false,
          "concurrently": false,
          "method": "btree",
          "with": {}
        },
        "ticket_building_idx": {
          "name": "ticket_building_idx",
          "columns": [
            {
              "expression": "building_id",
              "isExpression": false,
              "asc": true,
              "nulls": "last"
            }
          ],
          "isUnique": false,
          "concurrently": false,
          "method": "btree",
          "with": {}
        },
        "ticket_status_idx": {
          "name": "ticket_status_idx",
          "columns": [
            {
              "expression": "status",
              "isExpression": false,
              "asc": true,
              "nulls": "last"
            }
          ],
          "isUnique": false,
          "concurrently": false,
          "method": "btree",
          "with": {}
        },
        "ticket_created_by_idx": {
          "name": "ticket_created_by_idx",
          "columns": [
            {
              "expression": "created_by_id",
              "isExpression": false,
              "asc": true,
              "nulls": "last"
            }
          ],
          "isUnique": false,
          "concurrently": false,
          "method": "btree",
          "with": {}
        }
      },
      "foreignKeys": {
        "tickets_organization_id_organizations_id_fk": {
          "name": "tickets_organization_id_organizations_id_fk",
          "tableFrom": "tickets",
          "tableTo": "organizations",
          "columnsFrom": [
            "organization_id"
          ],
          "columnsTo": [
            "id"
          ],
          "onDelete": "no action",
          "onUpdate": "no action"
        },
        "tickets_building_id_buildings_id_fk": {
          "name": "tickets_building_id_buildings_id_fk",
          "tableFrom": "tickets",
          "tableTo": "buildings",
          "columnsFrom": [
            "building_id"
          ],
          "columnsTo": [
            "id"
          ],
          "onDelete": "no action",
          "onUpdate": "no action"
        },
        "tickets_contract_id_contracts_id_fk": {
          "name": "tickets_contract_id_contracts_id_fk",
          "tableFrom": "tickets",
          "tableTo": "contracts",
          "columnsFrom": [
            "contract_id"
          ],
          "columnsTo": [
            "id"
          ],
          "onDelete": "no action",
          "onUpdate": "no action"
        },
        "tickets_created_by_id_users_id_fk": {
          "name": "tickets_created_by_id_users_id_fk",
          "tableFrom": "tickets",
          "tableTo": "users",
          "columnsFrom": [
            "created_by_id"
          ],
          "columnsTo": [
            "id"
          ],
          "onDelete": "no action",
          "onUpdate": "no action"
        },
        "tickets_assigned_to_id_users_id_fk": {
          "name": "tickets_assigned_to_id_users_id_fk",
          "tableFrom": "tickets",
          "tableTo": "users",
          "columnsFrom": [
            "assigned_to_id"
          ],
          "columnsTo": [
            "id"
          ],
          "onDelete": "no action",
          "onUpdate": "no action"
        }
      },
      "compositePrimaryKeys": {},
      "uniqueConstraints": {},
      "policies": {},
      "checkConstraints": {},
      "isRLSEnabled": false
    },
    "public.users": {
      "name": "users",
      "schema": "",
      "columns": {
        "id": {
          "name": "id",
          "type": "uuid",
          "primaryKey": true,
          "notNull": true,
          "default": "gen_random_uuid()"
        },
        "email": {
          "name": "email",
          "type": "text",
          "primaryKey": false,
          "notNull": true
        },
        "email_verified": {
          "name": "email_verified",
          "type": "timestamp with time zone",
          "primaryKey": false,
          "notNull": false
        },
        "name": {
          "name": "name",
          "type": "text",
          "primaryKey": false,
          "notNull": false
        },
        "image": {
          "name": "image",
          "type": "text",
          "primaryKey": false,
          "notNull": false
        },
        "role": {
          "name": "role",
          "type": "text",
          "primaryKey": false,
          "notNull": true
        },
        "organization_id": {
          "name": "organization_id",
          "type": "uuid",
          "primaryKey": false,
          "notNull": true
        },
        "is_active": {
          "name": "is_active",
          "type": "boolean",
          "primaryKey": false,
          "notNull": false,
          "default": true
        },
        "created_at": {
          "name": "created_at",
          "type": "timestamp with time zone",
          "primaryKey": false,
          "notNull": false,
          "default": "now()"
        },
        "updated_at": {
          "name": "updated_at",
          "type": "timestamp with time zone",
          "primaryKey": false,
          "notNull": false,
          "default": "now()"
        }
      },
      "indexes": {
        "user_email_idx": {
          "name": "user_email_idx",
          "columns": [
            {
              "expression": "email",
              "isExpression": false,
              "asc": true,
              "nulls": "last"
            }
          ],
          "isUnique": false,
          "concurrently": false,
          "method": "btree",
          "with": {}
        },
        "user_org_idx": {
          "name": "user_org_idx",
          "columns": [
            {
              "expression": "organization_id",
              "isExpression": false,
              "asc": true,
              "nulls": "last"
            }
          ],
          "isUnique": false,
          "concurrently": false,
          "method": "btree",
          "with": {}
        }
      },
      "foreignKeys": {
        "users_organization_id_organizations_id_fk": {
          "name": "users_organization_id_organizations_id_fk",
          "tableFrom": "users",
          "tableTo": "organizations",
          "columnsFrom": [
            "organization_id"
          ],
          "columnsTo": [
            "id"
          ],
          "onDelete": "no action",
          "onUpdate": "no action"
        }
      },
      "compositePrimaryKeys": {},
      "uniqueConstraints": {
        "users_email_unique": {
          "name": "users_email_unique",
          "nullsNotDistinct": false,
          "columns": [
            "email"
          ]
        }
      },
      "policies": {},
      "checkConstraints": {},
      "isRLSEnabled": false
    },
    "public.verification_tokens": {
      "name": "verification_tokens",
      "schema": "",
      "columns": {
        "identifier": {
          "name": "identifier",
          "type": "text",
          "primaryKey": false,
          "notNull": true
        },
        "token": {
          "name": "token",
          "type": "text",
          "primaryKey": false,
          "notNull": true
        },
        "expires": {
          "name": "expires",
          "type": "timestamp with time zone",
          "primaryKey": false,
          "notNull": true
        }
      },
      "indexes": {
        "verification_compound_idx": {
          "name": "verification_compound_idx",
          "columns": [
            {
              "expression": "identifier",
              "isExpression": false,
              "asc": true,
              "nulls": "last"
            },
            {
              "expression": "token",
              "isExpression": false,
              "asc": true,
              "nulls": "last"
            }
          ],
          "isUnique": false,
          "concurrently": false,
          "method": "btree",
          "with": {}
        }
      },
      "foreignKeys": {},
      "compositePrimaryKeys": {},
      "uniqueConstraints": {},
      "policies": {},
      "checkConstraints": {},
      "isRLSEnabled": false
    }
  },
  "enums": {},
  "schemas": {},
  "sequences": {},
  "roles": {},
  "policies": {},
  "views": {},
  "_meta": {
    "columns": {},
    "schemas": {},
    "tables": {}
  }
}